lord_of_the_rings_sdk/__init__.py
lord_of_the_rings_sdk/lord_of_the_rings_sdk.py
lord_of_the_rings_sdk_seanmavley-1.0.0.dist-info/METADATA
lord_of_the_rings_sdk_seanmavley-1.0.0.dist-info/WHEEL
lord_of_the_rings_sdk_seanmavley-1.0.0.dist-info/top_level.txt
lord_of_the_rings_sdk_seanmavley-1.0.0.dist-info/RECORD
