Metadata-Version: 2.1
Name: lord-of-the-rings-sdk-seanmavley
Version: 1.0.0
Summary: SDK for the Lord of the Rings API
Home-page: https://github.com/seanmavley/lord-of-the-rings-sdk
Author: Rexford
Author-email: seanmavley@gmail.com
License: UNKNOWN
Platform: UNKNOWN
Classifier: Development Status :: 5 - Production/Stable
Classifier: Intended Audience :: Developers
Classifier: License :: OSI Approved :: MIT License
Classifier: Programming Language :: Python :: 3
Classifier: Programming Language :: Python :: 3.6
Classifier: Programming Language :: Python :: 3.7
Classifier: Programming Language :: Python :: 3.8
Classifier: Programming Language :: Python :: 3.9
Requires-Dist: requests
